{
  "id": "rswZSaMV83moe6jEcYKuX4",
  "rootNodeId": "sbqzEMC1I8",
  "nodes": {
    "sbqzEMC1I8": {
      "type": { "resolvedName": "StyleBox" },
      "isCanvas": true,
      "props": {
        "events": [],
        "serverSideRef": "notifBar",
        "style": {
          "backgroundColor": " #E9ECF1",
          "display": "flex",
          "flexDirection": "column",
          "justifyContent": "flex-start",
          "alignItems": "stretch",
          "flexWrap": "nowrap",
          "alignContent": "space-around",
          "gap": "3%"
        },
        "classNames": ["notifBar_responsive"],
        "iterableChild": true
      },
      "displayName": "Stylebox",
      "custom": {},
      "parent": "ROOT",
      "hidden": false,
      "nodes": [
        "UjBJu46lzE",
        "icBNN5rpln",
        "4vMaoJnD1g",
        "L1YQGAyau4",
        "V4tsqw8tPu"
      ],
      "linkedNodes": {}
    },
    "UjBJu46lzE": {
      "type": { "resolvedName": "Icon" },
      "isCanvas": false,
      "props": {
        "classNames": [],
        "events": [],
        "icon": "fa-angle-left",
        "style": {
          "textAlign": "right",
          "color": "#777E90",
          "fontSize": "18px",
          "position": "absolute",
          "right": "10px",
          "zIndex": "1",
          "cursor": "pointer"
        }
      },
      "displayName": "Icon",
      "custom": {},
      "parent": "sbqzEMC1I8",
      "hidden": false,
      "nodes": [],
      "linkedNodes": {}
    },
    "icBNN5rpln": {
      "type": { "resolvedName": "Icon" },
      "isCanvas": false,
      "props": {
        "classNames": [],
        "events": [],
        "icon": "fa-close",
        "style": {
          "textAlign": "right",
          "color": "#777E90",
          "fontSize": "18px",
          "position": "absolute",
          "right": "10px",
          "zIndex": "1",
          "cursor": "pointer"
        }
      },
      "displayName": "Icon",
      "custom": {},
      "parent": "sbqzEMC1I8",
      "hidden": false,
      "nodes": [],
      "linkedNodes": {}
    },
    "4vMaoJnD1g": {
      "type": { "resolvedName": "StyleBox" },
      "isCanvas": true,
      "props": {
        "events": [],
        "style": {
          "paddingLeft": "0px",
          "paddingRight": "0px",
          "paddingBottom": "0px",
          "paddingTop": "0px",
          "display": "flex",
          "justifyContent": "center",
          "alignItems": "center"
        },
        "iterableChild": true
      },
      "displayName": "Stylebox",
      "custom": {},
      "parent": "sbqzEMC1I8",
      "hidden": false,
      "nodes": ["pgHcyy3f4E", "RR4PBLjMmT"],
      "linkedNodes": {}
    },
    "pgHcyy3f4E": {
      "type": { "resolvedName": "Image" },
      "isCanvas": false,
      "props": {
        "classNames": ["notifBar_userAvatar"],
        "events": [],
        "style": {
          "height": "49px",
          "width": "49px",
          "borderRadius": "50px",
          "minWidth": "49px",
          "minHeight": "49px"
        },
        "imgSrc": "",
        "datasource": "#user.avatar#"
      },
      "displayName": "Image",
      "custom": {},
      "parent": "4vMaoJnD1g",
      "hidden": false,
      "nodes": [],
      "linkedNodes": {}
    },
    "RR4PBLjMmT": {
      "type": { "resolvedName": "StyleBox" },
      "isCanvas": true,
      "props": { "events": [], "iterableChild": true },
      "displayName": "Stylebox",
      "custom": {},
      "parent": "4vMaoJnD1g",
      "hidden": false,
      "nodes": ["Bg8B_3M3zj", "E-J4cDwoz7"],
      "linkedNodes": {}
    },
    "Bg8B_3M3zj": {
      "type": { "resolvedName": "Text" },
      "isCanvas": false,
      "props": {
        "events": [],
        "doc": [
          {
            "type": "paragraph",
            "children": [
              {
                "text": "fullName",
                "italic": false,
                "underlined": false,
                "strikethrough": false
              }
            ]
          }
        ],
        "datasource": "",
        "style": {
          "color": "#000000",
          "textTransform": "capitalize",
          "fontWeight": "500"
        },
        "classNames": ["notifBar_userNameSize"],
        "iterableChild": true
      },
      "displayName": "Text",
      "custom": {},
      "parent": "RR4PBLjMmT",
      "hidden": false,
      "nodes": [],
      "linkedNodes": {}
    },
    "E-J4cDwoz7": {
      "type": { "resolvedName": "Text" },
      "isCanvas": false,
      "props": {
        "events": [],
        "doc": [
          {
            "type": "paragraph",
            "children": [
              {
                "text": "role",
                "bold": false,
                "italic": false,
                "underlined": false,
                "strikethrough": false
              }
            ]
          }
        ],
        "datasource": "",
        "style": { "color": "#A0A6B1" },
        "iterableChild": true
      },
      "displayName": "Text",
      "custom": {},
      "parent": "RR4PBLjMmT",
      "hidden": false,
      "nodes": [],
      "linkedNodes": {}
    },
    "L1YQGAyau4": {
      "type": { "resolvedName": "StyleBox" },
      "isCanvas": true,
      "props": {
        "events": [],
        "style": {
          "display": "flex",
          "alignItems": "center",
          "paddingLeft": "0px",
          "paddingRight": "0px",
          "paddingBottom": "0px",
          "paddingTop": "0px",
          "borderWidth": "1px",
          "borderRadius": "10px",
          "height": "35px",
          "justifyContent": "center",
          "backgroundColor": " #FFFFFF",
          "minHeight": "35px"
        },
        "iterableChild": true
      },
      "displayName": "Stylebox",
      "custom": {},
      "parent": "sbqzEMC1I8",
      "hidden": false,
      "nodes": ["RY48zmXaQ1", "m1IyTxwadB"],
      "linkedNodes": {}
    },
    "RY48zmXaQ1": {
      "type": { "resolvedName": "TextInput" },
      "isCanvas": false,
      "props": {
        "events": [],
        "placeholder": "placeholder",
        "label": "label",
        "labelPosition": "left",
        "style": {
          "borderStyle": "none",
          "position": "absolute",
          "zIndex": "1",
          "width": "100%",
          "height": "35px",
          "paddingLeft": "15%"
        },
        "iterableChild": true
      },
      "displayName": "Text Input",
      "custom": {},
      "parent": "L1YQGAyau4",
      "hidden": false,
      "nodes": [],
      "linkedNodes": { "label": "E4_h2u_x8f", "input": "cIfdoodBiK" }
    },
    "E4_h2u_x8f": {
      "type": { "resolvedName": "Label" },
      "isCanvas": false,
      "props": {
        "events": [],
        "moveable": false,
        "style": { "display": "none" },
        "deletable": true,
        "text": "SearchInput"
      },
      "displayName": "Label",
      "custom": {},
      "parent": "RY48zmXaQ1",
      "hidden": false,
      "nodes": [],
      "linkedNodes": {}
    },
    "cIfdoodBiK": {
      "type": { "resolvedName": "Input" },
      "isCanvas": false,
      "props": {
        "events": [],
        "deletable": false,
        "className": "fd-input w-full bg-transparent",
        "type": "text",
        "style": {
          "borderStyle": "none",
          "textAlign": "left",
          "color": "#777E90",
          "height": "24px"
        },
        "placeholder": "",
        "moveable": false,
        "readonly": false,
        "datasource": ""
      },
      "displayName": "Input",
      "custom": {},
      "parent": "RY48zmXaQ1",
      "hidden": false,
      "nodes": [],
      "linkedNodes": {}
    },
    "m1IyTxwadB": {
      "type": { "resolvedName": "Icon" },
      "isCanvas": false,
      "props": {
        "classNames": [],
        "events": [],
        "icon": "fa-search",
        "style": {
          "color": "#777E90",
          "position": "absolute",
          "left": "5%",
          "display": "block",
          "alignItems": "center",
          "justifyContent": "center",
          "marginRight": "5px"
        }
      },
      "displayName": "Icon",
      "custom": {},
      "parent": "L1YQGAyau4",
      "hidden": false,
      "nodes": [],
      "linkedNodes": {}
    },
    "V4tsqw8tPu": {
      "type": { "resolvedName": "StyleBox" },
      "isCanvas": true,
      "props": {
        "events": [],
        "style": {
          "paddingRight": "0px",
          "paddingBottom": "0px",
          "paddingTop": "0px",
          "paddingLeft": "0px",
          "display": "flex",
          "alignItems": "start",
          "justifyContent": "center",
          "flexDirection": "column",
          "gap": "5px"
        },
        "classNames": ["component_flexGrow"],
        "iterableChild": true
      },
      "displayName": "Stylebox",
      "custom": {},
      "parent": "sbqzEMC1I8",
      "hidden": false,
      "nodes": ["LCBtI6pi6h", "ejl0sk2l77"],
      "linkedNodes": {}
    },
    "LCBtI6pi6h": {
      "type": { "resolvedName": "Text" },
      "isCanvas": false,
      "props": {
        "events": [],
        "doc": [
          {
            "type": "paragraph",
            "children": [
              {
                "text": "Notifications",
                "bold": false,
                "italic": false,
                "underlined": false,
                "strikethrough": false
              }
            ]
          }
        ],
        "datasource": "",
        "style": { "fontSize": "18px", "color": "#777E90" },
        "iterableChild": true
      },
      "displayName": "Text",
      "custom": {},
      "parent": "V4tsqw8tPu",
      "hidden": false,
      "nodes": [],
      "linkedNodes": {}
    },
    "ejl0sk2l77": {
      "type": { "resolvedName": "StyleBox" },
      "isCanvas": true,
      "props": {
        "events": [],
        "style": {
          "paddingLeft": "0px",
          "paddingRight": "0px",
          "paddingBottom": "0px",
          "paddingTop": "0px"
        },
        "classNames": ["component_flexGrow"],
        "iterableChild": true
      },
      "displayName": "Stylebox",
      "custom": {},
      "parent": "V4tsqw8tPu",
      "hidden": false,
      "nodes": ["iCDBQwhddS"],
      "linkedNodes": {}
    },
    "iCDBQwhddS": {
      "type": { "resolvedName": "Matrix" },
      "isCanvas": false,
      "props": {
        "orientation": "vertical",
        "iterable": true,
        "classNames": [],
        "events": [],
        "style": {
          "display": "flex",
          "flexDirection": "column",
          "gap": "5%",
          "height": "100%",
          "borderStyle": "none"
        },
        "datasource": "#notices#",
        "gridProps": {
          "styleboxWidth": 1,
          "styleboxHeight": 130,
          "styleboxPercentWidth": "100%",
          "enableMosaic": false
        },
        "currentElement": "declinedNotif"
      },
      "displayName": "Matrix",
      "custom": {},
      "parent": "ejl0sk2l77",
      "hidden": false,
      "nodes": [],
      "linkedNodes": { "container": "uU8TzqFdWA" }
    },
    "uU8TzqFdWA": {
      "type": { "resolvedName": "StyleBox" },
      "isCanvas": true,
      "props": {
        "events": [],
        "style": {
          "display": "flex",
          "alignItems": "center",
          "paddingLeft": "0px",
          "paddingRight": "0px",
          "paddingBottom": "0px",
          "paddingTop": "0px",
          "borderRadius": "10px",
          "height": "130px"
        },
        "iterableChild": true
      },
      "displayName": "Stylebox",
      "custom": { "contentHeight": 130, "contentWidth": 251 },
      "parent": "iCDBQwhddS",
      "hidden": false,
      "nodes": ["EKwvxiQ814"],
      "linkedNodes": {}
    },
    "EKwvxiQ814": {
      "type": { "resolvedName": "StyleBox" },
      "isCanvas": true,
      "props": {
        "events": [],
        "style": {
          "backgroundColor": " #FFFFFF",
          "borderRadius": "10px",
          "display": "flex",
          "justifyContent": "center",
          "flexDirection": "column",
          "height": "125px"
        },
        "iterableChild": true
      },
      "displayName": "Stylebox",
      "custom": {},
      "parent": "uU8TzqFdWA",
      "hidden": false,
      "nodes": ["dWyx40laMd", "6MwgIazvba"],
      "linkedNodes": {}
    },
    "dWyx40laMd": {
      "type": { "resolvedName": "StyleBox" },
      "isCanvas": true,
      "props": {
        "events": [],
        "style": {
          "display": "flex",
          "alignItems": "center",
          "justifyContent": "flex-start",
          "paddingLeft": "0px",
          "paddingRight": "0px",
          "paddingBottom": "0px",
          "paddingTop": "0px",
          "gap": "10px",
          "borderBottomWidth": "1px",
          "textAlign": "justify"
        },
        "iterableChild": true
      },
      "displayName": "Stylebox",
      "custom": {},
      "parent": "EKwvxiQ814",
      "hidden": false,
      "nodes": ["NjdK2ai13d", "5Z7wcaDgjv"],
      "linkedNodes": {}
    },
    "NjdK2ai13d": {
      "type": { "resolvedName": "Image" },
      "isCanvas": false,
      "props": {
        "classNames": ["notifBar_userAvatar"],
        "events": [],
        "style": {
          "height": "40px",
          "width": "40px",
          "borderRadius": "50%",
          "minWidth": "40px",
          "maxWidth": "4px"
        },
        "datasource": ""
      },
      "displayName": "Image",
      "custom": {},
      "parent": "dWyx40laMd",
      "hidden": false,
      "nodes": [],
      "linkedNodes": {}
    },
    "5Z7wcaDgjv": {
      "type": { "resolvedName": "Text" },
      "isCanvas": false,
      "props": {
        "events": [],
        "doc": [
          {
            "type": "paragraph",
            "children": [
              {
                "bold": false,
                "italic": false,
                "underlined": false,
                "strikethrough": false,
                "text": "notice"
              }
            ]
          }
        ],
        "datasource": "",
        "style": { "fontSize": "1.1VH" },
        "iterableChild": true
      },
      "displayName": "Text",
      "custom": {},
      "parent": "dWyx40laMd",
      "hidden": false,
      "nodes": [],
      "linkedNodes": {}
    },
    "6MwgIazvba": {
      "type": { "resolvedName": "StyleBox" },
      "isCanvas": true,
      "props": {
        "events": [],
        "style": { "paddingTop": "0px", "paddingBottom": "0px" },
        "iterableChild": true
      },
      "displayName": "Stylebox",
      "custom": {},
      "parent": "EKwvxiQ814",
      "hidden": false,
      "nodes": ["b9baECTaLr", "DLeT8XMbn0"],
      "linkedNodes": {}
    },
    "b9baECTaLr": {
      "type": { "resolvedName": "StyleBox" },
      "isCanvas": true,
      "props": {
        "events": [],
        "style": { "display": "flex", "justifyContent": "space-between" },
        "iterableChild": true
      },
      "displayName": "Stylebox",
      "custom": {},
      "parent": "6MwgIazvba",
      "hidden": false,
      "nodes": ["0amAxVDwBY", "xnrQAG_NAy"],
      "linkedNodes": {}
    },
    "0amAxVDwBY": {
      "type": { "resolvedName": "Text" },
      "isCanvas": false,
      "props": {
        "events": [],
        "doc": [{ "type": "paragraph", "children": [{ "text": "status: " }] }],
        "datasource": "",
        "style": { "fontSize": "1vh", "textTransform": "capitalize" },
        "serverSideRef": "",
        "classNames": [],
        "iterableChild": true
      },
      "displayName": "Text",
      "custom": {},
      "parent": "b9baECTaLr",
      "hidden": false,
      "nodes": [],
      "linkedNodes": {}
    },
    "xnrQAG_NAy": {
      "type": { "resolvedName": "Text" },
      "isCanvas": false,
      "props": {
        "events": [],
        "doc": [{ "type": "paragraph", "children": [{ "text": "status" }] }],
        "datasource": "",
        "style": { "fontSize": "1vh", "textTransform": "capitalize" },
        "serverSideRef": "",
        "classNames": ["notifBar_notifStatus"],
        "iterableChild": true
      },
      "displayName": "Text",
      "custom": {},
      "parent": "b9baECTaLr",
      "hidden": false,
      "nodes": [],
      "linkedNodes": {}
    },
    "DLeT8XMbn0": {
      "type": { "resolvedName": "StyleBox" },
      "isCanvas": true,
      "props": {
        "events": [],
        "style": {
          "display": "flex",
          "paddingLeft": "0px",
          "paddingRight": "0px",
          "paddingBottom": "0px",
          "paddingTop": "0px",
          "justifyContent": "space-between",
          "alignItems": "center"
        },
        "iterableChild": true
      },
      "displayName": "Stylebox",
      "custom": {},
      "parent": "6MwgIazvba",
      "hidden": false,
      "nodes": ["Z6rYYA7w5O", "l25mT5sqv2"],
      "linkedNodes": {}
    },
    "Z6rYYA7w5O": {
      "type": { "resolvedName": "Button" },
      "isCanvas": false,
      "props": {
        "text": "Refuse",
        "classNames": [],
        "events": [],
        "iconPosition": "hidden",
        "style": {
          "display": "flex",
          "width": "auto",
          "backgroundColor": " #EBBEC6",
          "borderRadius": "27px",
          "fontSize": "1.3vh"
        }
      },
      "displayName": "Button",
      "custom": {},
      "parent": "DLeT8XMbn0",
      "hidden": false,
      "nodes": [],
      "linkedNodes": { "icon": "emdaOTHBBY" }
    },
    "emdaOTHBBY": {
      "type": { "resolvedName": "Icon" },
      "isCanvas": false,
      "props": { "classNames": [], "events": [], "icon": "fa-star" },
      "displayName": "Icon",
      "custom": {},
      "parent": "Z6rYYA7w5O",
      "hidden": false,
      "nodes": [],
      "linkedNodes": {}
    },
    "l25mT5sqv2": {
      "type": { "resolvedName": "Button" },
      "isCanvas": false,
      "props": {
        "text": "Accept",
        "classNames": [],
        "events": [],
        "iconPosition": "hidden",
        "style": {
          "display": "flex",
          "width": "auto",
          "backgroundColor": " #2E59BD",
          "borderRadius": "27px",
          "fontSize": "1.3vh"
        }
      },
      "displayName": "Button",
      "custom": {},
      "parent": "DLeT8XMbn0",
      "hidden": false,
      "nodes": [],
      "linkedNodes": { "icon": "P5WHiNfIcZ" }
    },
    "P5WHiNfIcZ": {
      "type": { "resolvedName": "Icon" },
      "isCanvas": false,
      "props": { "classNames": [], "events": [], "icon": "fa-star" },
      "displayName": "Icon",
      "custom": {},
      "parent": "l25mT5sqv2",
      "hidden": false,
      "nodes": [],
      "linkedNodes": {}
    }
  },
  "styles": [
    {
      "name": "component_flexGrow",
      "content": "self {\n\tflex-grow: 1;\n}",
      "parentId": null,
      "id": "-Qwvjyv-4qnawCTXbJ4k1",
      "scope": "local"
    }
  ]
}
